flask_mm/__about__.py
flask_mm/__init__.py
flask_mm/files.py
flask_mm/postprocess.py
flask_mm/utils.py
flask_mm/views.py
flask_mm/managers/__init__.py
flask_mm/managers/file.py
flask_mm/managers/image.py
flask_mm/storages/__init__.py
flask_mm/storages/local.py
flask_mm/storages/s3.py
tests/__init__.py
tests/conftest.py
tests/test_config.py
tests/test_image_manager.py
tests/test_local_file_manager.py
tests/test_local_image_manager.py
tests/test_s3_file_manager.py
tests/test_views.py
flask_mm-0.0.13.dev0.dist-info/LICENSE
flask_mm-0.0.13.dev0.dist-info/METADATA
flask_mm-0.0.13.dev0.dist-info/WHEEL
flask_mm-0.0.13.dev0.dist-info/entry_points.txt
flask_mm-0.0.13.dev0.dist-info/top_level.txt
flask_mm-0.0.13.dev0.dist-info/RECORD
